flask_route_checker/__init__.py
flask_route_checker/routes_checker.py
flask_route_checker-0.1.4.dist-info/licenses/LICENSE
flask_route_checker-0.1.4.dist-info/METADATA
flask_route_checker-0.1.4.dist-info/WHEEL
flask_route_checker-0.1.4.dist-info/entry_points.txt
flask_route_checker-0.1.4.dist-info/top_level.txt
flask_route_checker-0.1.4.dist-info/RECORD
