Metadata-Version: 2.4
Name: flask-route-checker
Version: 0.1.4
Summary: Check and auto-fix broken Flask route usage in templates
Author-email: Sidiq Olasode <sidiqolasode@gmail.com>
License: MIT
Requires-Python: >=3.8
License-File: LICENSE
Requires-Dist: colorama
Requires-Dist: rich
Requires-Dist: rapidfuzz
Requires-Dist: requests
Dynamic: license-file
